google/cloud/secretmanager/__init__.py
google/cloud/secretmanager/gapic_version.py
google/cloud/secretmanager/py.typed
google/cloud/secretmanager_v1/__init__.py
google/cloud/secretmanager_v1/gapic_metadata.json
google/cloud/secretmanager_v1/gapic_version.py
google/cloud/secretmanager_v1/py.typed
google/cloud/secretmanager_v1/services/__init__.py
google/cloud/secretmanager_v1/services/secret_manager_service/__init__.py
google/cloud/secretmanager_v1/services/secret_manager_service/async_client.py
google/cloud/secretmanager_v1/services/secret_manager_service/client.py
google/cloud/secretmanager_v1/services/secret_manager_service/pagers.py
google/cloud/secretmanager_v1/services/secret_manager_service/transports/__init__.py
google/cloud/secretmanager_v1/services/secret_manager_service/transports/base.py
google/cloud/secretmanager_v1/services/secret_manager_service/transports/grpc.py
google/cloud/secretmanager_v1/services/secret_manager_service/transports/grpc_asyncio.py
google/cloud/secretmanager_v1/services/secret_manager_service/transports/rest.py
google/cloud/secretmanager_v1/services/secret_manager_service/transports/rest_base.py
google/cloud/secretmanager_v1/types/__init__.py
google/cloud/secretmanager_v1/types/resources.py
google/cloud/secretmanager_v1/types/service.py
google/cloud/secretmanager_v1beta1/__init__.py
google/cloud/secretmanager_v1beta1/gapic_metadata.json
google/cloud/secretmanager_v1beta1/gapic_version.py
google/cloud/secretmanager_v1beta1/py.typed
google/cloud/secretmanager_v1beta1/services/__init__.py
google/cloud/secretmanager_v1beta1/services/secret_manager_service/__init__.py
google/cloud/secretmanager_v1beta1/services/secret_manager_service/async_client.py
google/cloud/secretmanager_v1beta1/services/secret_manager_service/client.py
google/cloud/secretmanager_v1beta1/services/secret_manager_service/pagers.py
google/cloud/secretmanager_v1beta1/services/secret_manager_service/transports/__init__.py
google_cloud_secret_manager-2.23.2.dist-info/LICENSE
google_cloud_secret_manager-2.23.2.dist-info/METADATA
google_cloud_secret_manager-2.23.2.dist-info/WHEEL
google_cloud_secret_manager-2.23.2.dist-info/top_level.txt
google_cloud_secret_manager-2.23.2.dist-info/RECORD
